core.cpython-312-x86_64-linux-gnu.so
libosim-1.0.0.dist-info/METADATA
libosim-1.0.0.dist-info/WHEEL
libosim-1.0.0.dist-info/top_level.txt
libosim-1.0.0.dist-info/RECORD
