Metadata-Version: 2.1
Name: libosim
Version: 1.0.0
Summary: RL training environment
Author: @PJutch, @mindholdr, @Victor2309msk, @Zaddebroni
Requires-Python: >=3.7
Provides-Extra: test
Requires-Dist: pytest >=6.0 ; extra == 'test'
